s2and_rust/__init__.py
s2and_rust/_s2and_rust.cpython-312-aarch64-linux-gnu.so
s2and_rust-0.30.0.dist-info/METADATA
s2and_rust-0.30.0.dist-info/WHEEL
s2and_rust-0.30.0.dist-info/RECORD
