Metadata-Version: 2.4
Name: s2and-rust
Version: 0.30.0
Summary: Rust extension for s2and
Author: Sergey Feldman, Daniel King, Shivashankar Subramanian
License: MIT
Requires-Python: >=3.11
